{"android_codingstyle.md":"309e4601","android_deployonline.md":"c5d2306f","android_description.md":"a6d04ffc","android_messagepush.md":"897f4423","android_preview.md":"94e2d1dd","android_quickstart.md":"5bfbfca2","demo_alert.md":"5b137331","index.md":"4ef30a52","ios_codingstyle.md":"e98633a9","ios_deployonline.md":"a58cfdfa","ios_description.md":"dc1cf948","ios_preview.md":"5d97b08b","ios_quickstart.md":"7f970c78","microservice_description.md":"4a038670","microservice_preview.md":"4f32c502","microservice_quickstart.md":"9fc925d3","sponsors_index.md":"b23cd1d0","vue3_description.md":"2d164404","vue3_preview.md":"f39a6362","vue3_quickstart.md":"052d83d9"}
